mlx/submodule_guardian/__init__.py
mlx/submodule_guardian/_version.py
mlx/submodule_guardian/discussion_template.mako
mlx/submodule_guardian/submodule_guardian.py
mlx_submodule_guardian-0.1.0.dist-info/licenses/LICENSE
mlx_submodule_guardian-0.1.0.dist-info/METADATA
mlx_submodule_guardian-0.1.0.dist-info/WHEEL
mlx_submodule_guardian-0.1.0.dist-info/entry_points.txt
mlx_submodule_guardian-0.1.0.dist-info/top_level.txt
mlx_submodule_guardian-0.1.0.dist-info/RECORD
