Metadata-Version: 2.4
Name: mlx.submodule_guardian
Version: 0.1.0
Summary: A python script that checks the status of submodules in a GitLab merge request.
Author-email: Joke Waumans <jwm@melexis.com>
License-Expression: Apache-2.0
Project-URL: Homepage, https://github.com/melexis/submodule-guardian
Project-URL: Documentation, https://github.com/melexis/submodule-guardian
Project-URL: Source, https://github.com/melexis/submodule-guardian
Project-URL: Tracker, https://github.com/melexis/submodule-guardian/issues
Keywords: Gitlab CI,submodules,merge request,discussion,resolved,unresolved,fail pipeline
Classifier: Development Status :: 4 - Beta
Classifier: Intended Audience :: Developers
Classifier: Operating System :: OS Independent
Classifier: Programming Language :: Python
Classifier: Programming Language :: Python :: 3
Classifier: Programming Language :: Python :: 3.9
Classifier: Programming Language :: Python :: 3.10
Classifier: Programming Language :: Python :: 3.11
Classifier: Programming Language :: Python :: 3.12
Classifier: Programming Language :: Python :: 3.13
Requires-Python: >=3.9
License-File: LICENSE
Requires-Dist: python-gitlab>=3.7.0
Requires-Dist: python-decouple<4.0,>=3.4
Requires-Dist: mako<2.0,>=1.1.2
Requires-Dist: rich<15.0,>=14.2.0
Dynamic: license-file
